quiet_nebula/__init__.py
quiet_nebula/analyzer.py
quiet_nebula/cli.py
quiet_nebula-0.2.0.dist-info/METADATA
quiet_nebula-0.2.0.dist-info/WHEEL
quiet_nebula-0.2.0.dist-info/entry_points.txt
quiet_nebula-0.2.0.dist-info/top_level.txt
quiet_nebula-0.2.0.dist-info/RECORD
