Metadata-Version: 2.1
Name: quiet-nebula
Version: 0.2.0
Summary: A package to analyze sales data from a CSV file.
Author: Semyon Drozdov
Author-email: Semyon Drozdov <s.drozdov@edu.centraluniversity.ru>
Requires-Dist: pandas
